[
    {
        "fdesde": "2022-10-21",
        "fhasta": "2022-10-27",
        "importeReserva": 750,
        "importeTotal": "1500",
        "pet": {
            "nombre": "Perruno",
            "raza": "Perro",
            "tamano": "Grande",
            "planVacunacion": "\/TP-FINAL-2022\/Views\/\/img\/uploads\/planVACUNACON.jpg",
            "observacionesGrals": "Buen Perro",
            "video": "\/TP-FINAL-2022\/Views\/\/img\/uploads\/Rana - 113403.mp4",
            "imagen": "\/TP-FINAL-2022\/Views\/\/img\/uploads\/perro.jpg"
        },
        "keeper": {
            "nombreUser": "Decoud",
            "contrasena": "1234",
            "tipodeCuenta": "Keeper",
            "tipoMascota": [
                "Chica",
                "Mediana",
                "Grande"
            ],
            "remuneracion": "1500",
            "nombre": "Nahuel",
            "apellido": "Inglesias",
            "DNI": "22344535",
            "telefono": "2234559528"
        }
    }
]